sayuDB/__init__.py
sayuDB/__main__.py
sayuDB/processor.py
sayuDB/remote.py
sayuDB/server.py
sayuDB-0.0.4.dist-info/LICENSE
sayuDB-0.0.4.dist-info/METADATA
sayuDB-0.0.4.dist-info/WHEEL
sayuDB-0.0.4.dist-info/top_level.txt
sayuDB-0.0.4.dist-info/RECORD
