Metadata-Version: 2.1
Name: sayuDB
Version: 0.0.4
Summary: Database management system based on python and JSON.
Home-page: https://github.com/Arsybai/sayuDB
Author: Arsybai
Author-email: me@arsybai.com
License: MIT
Keywords: database
License-File: LICENSE
Requires-Dist: requests
Requires-Dist: tabulate
Requires-Dist: flask
